EcoStackML/__init__.py
EcoStackML/evaluation/__init__.py
EcoStackML/evaluation/evaluation_metrics.py
EcoStackML/preprocessing/__init__.py
EcoStackML/preprocessing/data_preprocessing.py
EcoStackML/scripts/__init__.py
EcoStackML/scripts/run_stacking.py
EcoStackML/stacking/__init__.py
EcoStackML/stacking/stacking.py
EcoStackML-0.1.0.dist-info/LICENCE
EcoStackML-0.1.0.dist-info/METADATA
EcoStackML-0.1.0.dist-info/WHEEL
EcoStackML-0.1.0.dist-info/entry_points.txt
EcoStackML-0.1.0.dist-info/top_level.txt
EcoStackML-0.1.0.dist-info/RECORD
