Metadata-Version: 2.1
Name: EcoStackML
Version: 0.1.0
Summary: Biblioteka do generowania danych systematycznych środowiskowych z wykorzystaniem ML Stacking
Home-page: https://github.com/TyMill/EcoStackML
Author: Tymoteusz Miller
Author-email: me@tymoteuszmiller.dev
Classifier: Programming Language :: Python :: 3
Classifier: License :: OSI Approved :: MIT License
Classifier: Operating System :: OS Independent
Requires-Python: >=3.6
License-File: LICENCE
Requires-Dist: numpy
Requires-Dist: pandas
Requires-Dist: scikit-learn
Requires-Dist: tensorflow
Requires-Dist: keras
Requires-Dist: xgboost
